{
  "doorTeleporters": [
    {
      "destination": "HOME",
      "doorDirection": "BACKWARD",
      "number": 3,
      "id": 10,
      "transform": {
        "position": {
          "x": -1.0,
          "y": 0.0,
          "z": 7.0
        },
        "rotation": {
          "x": 0.0,
          "y": 90.0,
          "z": 0.0
        }
      },
      "isBuilt": true
    },
    {
      "destination": "HOME",
      "doorDirection": "BACKWARD",
      "number": 2,
      "id": 10,
      "transform": {
        "position": {
          "x": 4.0,
          "y": 0.0,
          "z": 4.0
        },
        "rotation": {
          "x": 0.0,
          "y": 270.0,
          "z": 0.0
        }
      },
      "isBuilt": true
    },
    {
      "destination": "HOME",
      "doorDirection": "BACKWARD",
      "number": 1,
      "id": 10,
      "transform": {
        "position": {
          "x": -1.0,
          "y": 0.0,
          "z": 3.0
        },
        "rotation": {
          "x": 0.0,
          "y": 90.0,
          "z": 0.0
        }
      },
      "isBuilt": true
    },
    {
      "destination": "HOME",
      "doorDirection": "BACKWARD",
      "number": 6,
      "id": 10,
      "transform": {
        "position": {
          "x": 4.0,
          "y": 0.0,
          "z": 12.0
        },
        "rotation": {
          "x": 0.0,
          "y": 270.0,
          "z": 0.0
        }
      },
      "isBuilt": true
    },
    {
      "destination": "HOME",
      "doorDirection": "BACKWARD",
      "number": 4,
      "id": 10,
      "transform": {
        "position": {
          "x": 4.0,
          "y": 0.0,
          "z": 8.0
        },
        "rotation": {
          "x": 0.0,
          "y": 270.0,
          "z": 0.0
        }
      },
      "isBuilt": true
    },
    {
      "destination": "HOME",
      "doorDirection": "BACKWARD",
      "number": 5,
      "id": 10,
      "transform": {
        "position": {
          "x": -1.0,
          "y": 0.0,
          "z": 11.0
        },
        "rotation": {
          "x": 0.0,
          "y": 90.0,
          "z": 0.0
        }
      },
      "isBuilt": true
    }
  ],
  "elevatorTeleporters": [
    {
      "destination": "TOWN_SQUARE",
      "id": 11,
      "transform": {
        "position": {
          "x": 3.0,
          "y": 0.0,
          "z": 0.0
        },
        "rotation": {
          "x": 0.0,
          "y": 0.0,
          "z": 0.0
        }
      },
      "isBuilt": true
    }
  ],
  "walls": [],
  "simpleDoors": [],
  "grounds": [],
  "packages": [],
  "buckets": [],
  "props": []
}